MANIFEST.in
README.rst
license.txt
requirements.txt
setup.py
test-requirements.txt
tox.ini
PyVRML97.egg-info/PKG-INFO
PyVRML97.egg-info/SOURCES.txt
PyVRML97.egg-info/dependency_links.txt
PyVRML97.egg-info/not-zip-safe
PyVRML97.egg-info/requires.txt
PyVRML97.egg-info/top_level.txt
vrml/__init__.py
vrml/_bytes.py
vrml/arrays.py
vrml/cache.py
vrml/copier.py
vrml/csscolors.py
vrml/event.py
vrml/field.py
vrml/fieldtypes.py
vrml/node.py
vrml/nodepath.py
vrml/olist.py
vrml/protofunctions.py
vrml/protonamespace.py
vrml/route.py
vrml/weakkeydictfix.py
vrml/weaklist.py
vrml/weaktuple.py
vrml/vrml200x/__init__.py
vrml/vrml200x/parser.py
vrml/vrml97/__init__.py
vrml/vrml97/_transformmatrix.py
vrml/vrml97/_transformmatrix_accel.py
vrml/vrml97/basenamespaces.py
vrml/vrml97/basenodes.py
vrml/vrml97/linearise.py
vrml/vrml97/nodepath.py
vrml/vrml97/nodetypes.py
vrml/vrml97/nurbs.py
vrml/vrml97/parseprocessor.py
vrml/vrml97/parser.py
vrml/vrml97/scenegraph.py
vrml/vrml97/script.py
vrml/vrml97/shaders.py
vrml/vrml97/transformmatrix.py