Metadata-Version: 1.1
Name: PyVRML97
Version: 2.3.1
Summary: VRML97 Scenegraph model for Python
Home-page: http://pyopengl.sourceforge.net/context/
Author: Mike C. Fletcher
Author-email: mcfletch@vrplumber.com
License: BSD
Keywords: VRML,VRML97,scenegraph
Platform: Win32
Platform: Linux
Platform: OS-X
Platform: Posix
Classifier: License :: OSI Approved :: BSD License
Classifier: Programming Language :: Python
Classifier: Programming Language :: C
Classifier: Topic :: Software Development :: Libraries :: Python Modules
Classifier: Topic :: Multimedia :: Graphics :: 3D Rendering
Classifier: Intended Audience :: Developers
